cloctui/__init__.py
cloctui/cli.py
cloctui/main.py
cloctui/py.typed
cloctui/spinner.py
cloctui/styles.tcss
cloctui-0.1.0.dist-info/METADATA
cloctui-0.1.0.dist-info/WHEEL
cloctui-0.1.0.dist-info/entry_points.txt
cloctui-0.1.0.dist-info/licenses/LICENSE
cloctui-0.1.0.dist-info/RECORD
